cosmic_ray_to_mutation_elements_adapter-1.0.1.dist-info/licenses/LICENSE
cr_to_stryker/__init__.py
cr_to_stryker/_version.py
cr_to_stryker/export_stryker_report.py
cr_to_stryker/constants/html_report_template.py
cr_to_stryker/constants/mutation_testing_element.py
cr_to_stryker/resources/__init__.py
cr_to_stryker/resources/mutation-testing-elements.js
cosmic_ray_to_mutation_elements_adapter-1.0.1.dist-info/METADATA
cosmic_ray_to_mutation_elements_adapter-1.0.1.dist-info/WHEEL
cosmic_ray_to_mutation_elements_adapter-1.0.1.dist-info/entry_points.txt
cosmic_ray_to_mutation_elements_adapter-1.0.1.dist-info/top_level.txt
cosmic_ray_to_mutation_elements_adapter-1.0.1.dist-info/RECORD
