Metadata-Version: 2.4
Name: cosmic-ray-to-mutation-elements-adapter
Version: 1.0.1
Summary: Adapter to show cosmic-ray python mutation report in stryker's mutation testing elements format
Author-email: Kiran Kashyap <kiran.kashyap.ds@gmail.com>, Vivek Ganesan <vivek@vivekganesan.com>
Requires-Python: >=3.10
License-File: LICENSE
Dynamic: license-file
